spsuite
