Metadata-Version: 1.0
Name: spsuite
Version: 1.0.2
Summary: Command line utilities to manage ServerPilot provisioned servers.
Home-page: https://github.com/rehmatworks/spsuite
Author: Rehmat Alam
Author-email: contact@rehmat.works
License: MIT
Platform: UNKNOWN
